[
    {
        "datetime": "2023-12-15T06:45:00.000",
        "avg_db": 13.0966666667,
        "event_type": "none"
    },
    {
        "datetime": "2023-12-15T07:00:00.000",
        "avg_db": 33.9466666667,
        "event_type": "snore",
        "snore_start": "06-45-12.153",
        "m4a_file": "https://www.google.com/make-it-longer-to-calculate-worst-case-scenario-and-generally-aws-s3-paths-are-so-long"
    },
    {
        "datetime": "2023-12-15T07:15:00.000",
        "avg_db": 47.8833333333,
        "event_type": "none"
    },
    {
        "datetime": "2023-12-15T07:30:00.000",
        "avg_db": 55.586,
        "event_type": "none"
    },
    {
        "datetime": "2023-12-15T07:45:00.000",
        "avg_db": 53.9833333333,
        "event_type": "none"
    },
    {
        "datetime": "2023-12-15T08:00:00.000",
        "avg_db": 45.506,
        "event_type": "snore",
        "snore_start": "06-45-12.153",
        "m4a_file": "https://www.google.com/make-it-longer-to-calculate-worst-case-scenario-and-generally-aws-s3-paths-are-so-long"
    },
    {
        "datetime": "2023-12-15T08:15:00.000",
        "avg_db": 44.162,
        "event_type": "none"
    },
    {
        "datetime": "2023-12-15T08:30:00.000",
        "avg_db": 51.41,
        "event_type": "none"
    },
    {
        "datetime": "2023-12-15T08:45:00.000",
        "avg_db": 50.0893333333,
        "event_type": "none"
    },
    {
        "datetime": "2023-12-15T09:00:00.000",
        "avg_db": 35.9253333333,
        "event_type": "none"
    },
    {
        "datetime": "2023-12-15T09:15:00.000",
        "avg_db": 47.1066666667,
        "event_type": "snore",
        "snore_start": "06-45-12.153",
        "m4a_file": "https://www.google.com/make-it-longer-to-calculate-worst-case-scenario-and-generally-aws-s3-paths-are-so-long"
    },
    {
        "datetime": "2023-12-15T09:30:00.000",
        "avg_db": 48.872,
        "event_type": "none"
    },
    {
        "datetime": "2023-12-15T09:45:00.000",
        "avg_db": 34.5226666667,
        "event_type": "snore",
        "snore_start": "06-45-12.153",
        "m4a_file": "https://www.google.com/make-it-longer-to-calculate-worst-case-scenario-and-generally-aws-s3-paths-are-so-long"
    },
    {
        "datetime": "2023-12-15T10:00:00.000",
        "avg_db": 48.014,
        "event_type": "none"
    },
    {
        "datetime": "2023-12-15T10:15:00.000",
        "avg_db": 44.286,
        "event_type": "none"
    },
    {
        "datetime": "2023-12-15T10:30:00.000",
        "avg_db": 39.808,
        "event_type": "none"
    },
    {
        "datetime": "2023-12-15T10:45:00.000",
        "avg_db": 40.7126666667,
        "event_type": "snore",
        "snore_start": "06-45-12.153",
        "m4a_file": "https://www.google.com/make-it-longer-to-calculate-worst-case-scenario-and-generally-aws-s3-paths-are-so-long"
    },
    {
        "datetime": "2023-12-15T11:00:00.000",
        "avg_db": 42.0873333333,
        "event_type": "none"
    },
    {
        "datetime": "2023-12-15T11:15:00.000",
        "avg_db": 48.6766666667,
        "event_type": "none"
    },
    {
        "datetime": "2023-12-15T11:30:00.000",
        "avg_db": 46.5326666667,
        "event_type": "snore",
        "snore_start": "06-45-12.153",
        "m4a_file": "https://www.google.com/make-it-longer-to-calculate-worst-case-scenario-and-generally-aws-s3-paths-are-so-long"
    },
    {
        "datetime": "2023-12-15T11:45:00.000",
        "avg_db": 41.102,
        "event_type": "snore",
        "snore_start": "06-45-12.153",
        "m4a_file": "https://www.google.com/make-it-longer-to-calculate-worst-case-scenario-and-generally-aws-s3-paths-are-so-long"
    },
    {
        "datetime": "2023-12-15T12:00:00.000",
        "avg_db": 44.32,
        "event_type": "none"
    },
    {
        "datetime": "2023-12-15T12:15:00.000",
        "avg_db": 39.3226666667,
        "event_type": "none"
    },
    {
        "datetime": "2023-12-15T12:30:00.000",
        "avg_db": 49.7846666667,
        "event_type": "none"
    },
    {
        "datetime": "2023-12-15T12:45:00.000",
        "avg_db": 58.2773333333,
        "event_type": "none"
    },
    {
        "datetime": "2023-12-15T13:00:00.000",
        "avg_db": 47.608,
        "event_type": "none"
    },
    {
        "datetime": "2023-12-15T13:15:00.000",
        "avg_db": 36.3473333333,
        "event_type": "snore",
        "snore_start": "06-45-12.153",
        "m4a_file": "https://www.google.com/make-it-longer-to-calculate-worst-case-scenario-and-generally-aws-s3-paths-are-so-long"
    },
    {
        "datetime": "2023-12-15T13:30:00.000",
        "avg_db": 45.9666666667,
        "event_type": "snore",
        "snore_start": "06-45-12.153",
        "m4a_file": "https://www.google.com/make-it-longer-to-calculate-worst-case-scenario-and-generally-aws-s3-paths-are-so-long"
    },
    {
        "datetime": "2023-12-15T13:45:00.000",
        "avg_db": 35.0766666667,
        "event_type": "none"
    },
    {
        "datetime": "2023-12-15T14:00:00.000",
        "avg_db": 47.21,
        "event_type": "snore",
        "snore_start": "06-45-12.153",
        "m4a_file": "https://www.google.com/make-it-longer-to-calculate-worst-case-scenario-and-generally-aws-s3-paths-are-so-long"
    },
    {
        "datetime": "2023-12-15T14:15:00.000",
        "avg_db": 49.2046666667,
        "event_type": "snore",
        "snore_start": "06-45-12.153",
        "m4a_file": "https://www.google.com/make-it-longer-to-calculate-worst-case-scenario-and-generally-aws-s3-paths-are-so-long"
    },
    {
        "datetime": "2023-12-15T14:30:00.000",
        "avg_db": 40.8533333333,
        "event_type": "none"
    },
    {
        "datetime": "2023-12-15T14:45:00.000",
        "avg_db": 39.69,
        "event_type": "none"
    },
    {
        "datetime": "2023-12-15T15:00:00.000",
        "avg_db": 48.372,
        "event_type": "none"
    },
    {
        "datetime": "2023-12-15T15:15:00.000",
        "avg_db": 51.6706666667,
        "event_type": "none"
    },
    {
        "datetime": "2023-12-15T15:30:00.000",
        "avg_db": 30.9193333333,
        "event_type": "none"
    },
    {
        "datetime": "2023-12-15T15:45:00.000",
        "avg_db": 43.4,
        "event_type": "snore",
        "snore_start": "06-45-12.153",
        "m4a_file": "https://www.google.com/make-it-longer-to-calculate-worst-case-scenario-and-generally-aws-s3-paths-are-so-long"
    },
    {
        "datetime": "2023-12-15T16:00:00.000",
        "avg_db": 49.0213333333,
        "event_type": "none"
    },
    {
        "datetime": "2023-12-15T16:15:00.000",
        "avg_db": 45.4313333333,
        "event_type": "none"
    },
    {
        "datetime": "2023-12-15T16:30:00.000",
        "avg_db": 33.516,
        "event_type": "snore",
        "snore_start": "06-45-12.153",
        "m4a_file": "https://www.google.com/make-it-longer-to-calculate-worst-case-scenario-and-generally-aws-s3-paths-are-so-long"
    },
    {
        "datetime": "2023-12-15T16:45:00.000",
        "avg_db": 28.9766666667,
        "event_type": "snore",
        "snore_start": "06-45-12.153",
        "m4a_file": "https://www.google.com/make-it-longer-to-calculate-worst-case-scenario-and-generally-aws-s3-paths-are-so-long"
    }
]